winpwn/__init__.py
winpwn/context.py
winpwn/dbg.py
winpwn/misc.py
winpwn/var.py
winpwn/win.py
winpwn/winpwn.py
mypwn-0.0.1.dist-info/METADATA
mypwn-0.0.1.dist-info/WHEEL
mypwn-0.0.1.dist-info/top_level.txt
mypwn-0.0.1.dist-info/RECORD
